aircraft_classifiers_jme45/__about__.py
aircraft_classifiers_jme45/__init__.py
aircraft_classifiers_jme45/aircraft_types.py
aircraft_classifiers_jme45/classifiers.py
aircraft_classifiers_jme45/parameters.py
aircraft_classifiers_jme45-0.3.1.dist-info/METADATA
aircraft_classifiers_jme45-0.3.1.dist-info/WHEEL
aircraft_classifiers_jme45-0.3.1.dist-info/licenses/LICENSE
aircraft_classifiers_jme45-0.3.1.dist-info/RECORD
